setup.cfg
setup.py
PyInfinity/__init__.py
pyinfi.egg-info/PKG-INFO
pyinfi.egg-info/SOURCES.txt
pyinfi.egg-info/dependency_links.txt
pyinfi.egg-info/top_level.txt