Metadata-Version: 2.1
Name: pyinfi
Version: 0.0.1
Summary: Framework PyInfinity.
Author: Matvei K., Nikita M., Denis G.
Author-email: organisator.bibliotek.py@gmail.com
License: Use allowed with software mention only.
Classifier: License :: Other/Proprietary License
Classifier: Programming Language :: Python :: 3
Classifier: Programming Language :: Python :: 3.11
Classifier: Operating System :: Microsoft :: Windows
